laba8/__init__.py
laba8/rectangle.py
laba8/sr1.py
laba81-0.1.2.dist-info/licenses/LICENSE
laba81-0.1.2.dist-info/METADATA
laba81-0.1.2.dist-info/WHEEL
laba81-0.1.2.dist-info/RECORD
