Metadata-Version: 2.4
Name: laba81
Version: 0.1.2
Summary: 
License-File: LICENSE
Author: Soap
Author-email: artyom.krivoxin@mail.ru
Requires-Python: >=3.14
Classifier: Programming Language :: Python :: 3
Classifier: Programming Language :: Python :: 3.14
Requires-Dist: requests (>=2.32.5,<3.0.0)
Project-URL: Homepage, https://github.com/SOAP848/laba8
Project-URL: Repository, https://github.com/SOAP848/laba8.git
